{
  "computed_at": "2026-03-29T18:51:55.209487",
  "total_containers": 1,
  "storage_mode": "hdfs",
  "type_distribution": {
    "import": {
      "count": 1,
      "percentage": 100.0,
      "avg_weight_t": 20.0
    }
  },
  "size_distribution": {
    "20ft": {
      "count": 1,
      "percentage": 100.0,
      "avg_weight_t": 20.0
    }
  },
  "weight_stats": {
    "avg_t": 20.0,
    "min_t": 20.0,
    "max_t": 20.0,
    "stddev_t": 0.0
  },
  "time_window": {
    "earliest_departure": "2026-03-25T10:00:00",
    "latest_departure": "2026-03-25T10:00:00"
  },
  "pipeline_quality": {
    "total_raw_ingested": 10,
    "total_after_silver": 1,
    "duplicates_removed": 1,
    "invalid_removed": 8,
    "quality_score_pct": 10.0
  }
}